{
  "session_metadata": {
    "session_dir": "logs/golfbot_20250617_190019",
    "start_time": "2025-06-17T19:00:19.772285",
    "duration_seconds": 23.91408920288086,
    "total_frames": 64,
    "average_fps": 2.6762466032906707
  },
  "detection_stats": {
    "total_balls_detected": 29,
    "total_collections": 0,
    "collection_rate": 0.0,
    "errors_logged": 15
  },
  "competition_result": {},
  "files": {
    "telemetry_log": "logs/golfbot_20250617_190019/telemetry.jsonl",
    "summary": "logs/golfbot_20250617_190019/session_summary.json"
  }
}